usd2mjcf/__init__.py
usd2mjcf-0.0.1.dist-info/METADATA
usd2mjcf-0.0.1.dist-info/WHEEL
usd2mjcf-0.0.1.dist-info/top_level.txt
usd2mjcf-0.0.1.dist-info/RECORD
